{
  "hash": "e404dcd0",
  "configHash": "75f983ed",
  "lockfileHash": "6236a597",
  "browserHash": "1f2c4b1b",
  "optimized": {
    "lucide-react": {
      "src": "../../node_modules/lucide-react/dist/esm/lucide-react.mjs",
      "file": "lucide-react.js",
      "fileHash": "85561ba5",
      "needsInterop": false
    },
    "react-dom/client": {
      "src": "../../node_modules/react-dom/client.js",
      "file": "react-dom_client.js",
      "fileHash": "efa4e3dc",
      "needsInterop": true
    },
    "react-router-dom": {
      "src": "../../node_modules/react-router-dom/dist/index.mjs",
      "file": "react-router-dom.js",
      "fileHash": "20c5ae7d",
      "needsInterop": false
    },
    "react": {
      "src": "../../node_modules/react/index.js",
      "file": "react.js",
      "fileHash": "2cb436af",
      "needsInterop": true
    },
    "react/jsx-dev-runtime": {
      "src": "../../node_modules/react/jsx-dev-runtime.js",
      "file": "react_jsx-dev-runtime.js",
      "fileHash": "8e23159e",
      "needsInterop": true
    }
  },
  "chunks": {
    "react-CZunmVaX": {
      "file": "react-CZunmVaX.js",
      "isDynamicEntry": false
    },
    "react-dom-DlAeUGhR": {
      "file": "react-dom-DlAeUGhR.js",
      "isDynamicEntry": false
    }
  }
}